{
  "update_id": 942160573,
  "channel_post": {
    "message_id": 292,
    "chat": {
      "id": "-1001104220133",
      "title": "NewsDesio",
      "username": "newsdesio",
      "type": "channel"
    },
    "date": 1499689453,
    "text": "Qui Brianza\n     http://quibrianza.it/cronaca/desio/si-contendono-il-marciapiede-per-chiedere-l-elemosina-botte-da-orbi-in-due-all-ospedale.html",
    "entities": [
      {
        "type": "url",
        "offset": 17,
        "length": 127
      }
    ]
  }
}