{
  "update_id": 202413065,
  "channel_post": {
    "message_id": 2281,
    "chat": {
      "id": "-1001077404345",
      "title": "DesioChannel",
      "username": "infodesio",
      "type": "channel"
    },
    "date": 1509641777,
    "text": "INTEGRAZIONE DELL’IMPEGNO DI SPESA PER LA FORNITURA DI DISPOSITIVI DI PROTEZIONE INDIVIDUALE PER I VOLONTARI DELLA PROTEZIONE CIVILE E DEL VERDE PUBBLICO. EURO 4.300,00 I.V.A. COMPRESA. CODICE CIG Z822065862. \nhttp://desio.trasparenza-valutazione-merito.it/web/albo/storico-atti/-/papca/display/3620383",
    "entities": [
      {
        "type": "url",
        "offset": 210,
        "length": 92
      }
    ]
  }
}