{
  "update_id": 202413774,
  "channel_post": {
    "message_id": 2803,
    "chat": {
      "id": "-1001077404345",
      "title": "DesioChannel",
      "username": "infodesio",
      "type": "channel"
    },
    "date": 1514547108,
    "text": "DEFINIZIONE DEL CONTRATTO DI LOCAZIONE DELL'ALLOGGIO SITO IN VIA OLMETTO N. 48, RELATIVO ALLA SIG.RA T.L. \nhttp://desio.trasparenza-valutazione-merito.it/web/albo/storico-atti/-/papca/display/3767792",
    "entities": [
      {
        "type": "url",
        "offset": 107,
        "length": 92
      }
    ]
  }
}