{
  "update_id": 202413499,
  "channel_post": {
    "message_id": 2582,
    "chat": {
      "id": "-1001077404345",
      "title": "DesioChannel",
      "username": "infodesio",
      "type": "channel"
    },
    "date": 1512995453,
    "text": "MOBILITA' ABITATIVA NUCLEO FAMILIARE SIG.RA R.C. - VIA FIUME, 1 \nhttp://desio.trasparenza-valutazione-merito.it/web/albo/storico-atti/-/papca/display/3713955",
    "entities": [
      {
        "type": "url",
        "offset": 65,
        "length": 92
      }
    ]
  }
}